[
  {
    "code": "540501",
    "name": "乃东区"
  },
  {
    "code": "540502",
    "name": "扎囊县"
  },
  {
    "code": "540503",
    "name": "贡嘎县"
  },
  {
    "code": "540504",
    "name": "桑日县"
  },
  {
    "code": "540505",
    "name": "琼结县"
  },
  {
    "code": "540506",
    "name": "曲松县"
  },
  {
    "code": "540507",
    "name": "措美县"
  },
  {
    "code": "540508",
    "name": "洛扎县"
  },
  {
    "code": "540509",
    "name": "加查县"
  },
  {
    "code": "540510",
    "name": "隆子县"
  },
  {
    "code": "540511",
    "name": "浪卡子县"
  },
  {
    "code": "540512",
    "name": "错那市"
  }
]